pyrelational/__init__.py
pyrelational/types.py
pyrelational/version.py
pyrelational/data_managers/__init__.py
pyrelational/data_managers/data_manager.py
pyrelational/datasets/__init__.py
pyrelational/datasets/benchmark_datamanager.py
pyrelational/datasets/classification.py
pyrelational/datasets/regression.py
pyrelational/datasets/uci_datasets.py
pyrelational/informativeness/__init__.py
pyrelational/informativeness/classification.py
pyrelational/informativeness/regression.py
pyrelational/informativeness/task_agnostic.py
pyrelational/model_managers/__init__.py
pyrelational/model_managers/abstract_model_manager.py
pyrelational/model_managers/ensemble_model_manager.py
pyrelational/model_managers/lightning_model_manager.py
pyrelational/model_managers/mcdropout_model_manager.py
pyrelational/model_managers/model_utils.py
pyrelational/oracles/__init__.py
pyrelational/oracles/abstract_oracle.py
pyrelational/oracles/benchmark_oracle.py
pyrelational/pipeline/__init__.py
pyrelational/pipeline/pipeline.py
pyrelational/strategies/__init__.py
pyrelational/strategies/abstract_strategy.py
pyrelational/strategies/classification/__init__.py
pyrelational/strategies/classification/abstract_classification_strategy.py
pyrelational/strategies/classification/entropy_classification_strategy.py
pyrelational/strategies/classification/least_confidence_strategy.py
pyrelational/strategies/classification/marginal_confidence_strategy.py
pyrelational/strategies/classification/ratio_confidence_strategy.py
pyrelational/strategies/regression/__init__.py
pyrelational/strategies/regression/abstract_regression_strategy.py
pyrelational/strategies/regression/bald_strategy.py
pyrelational/strategies/regression/expected_improvement_strategy.py
pyrelational/strategies/regression/least_confidence_strategy.py
pyrelational/strategies/regression/mean_prediction_strategy.py
pyrelational/strategies/regression/thompson_sampling_strategy.py
pyrelational/strategies/regression/upper_confidence_bound_strategy.py
pyrelational-1.0.2.dist-info/LICENSE
pyrelational-1.0.2.dist-info/METADATA
pyrelational-1.0.2.dist-info/WHEEL
pyrelational-1.0.2.dist-info/top_level.txt
pyrelational-1.0.2.dist-info/RECORD
