Metadata-Version: 2.1
Name: pyrelational
Version: 1.0.2
Summary: Python tool box for quickly implementing active learning strategies
Home-page: https://github.com/RelationRx/pyrelational
Author: Relation Therapeutics
Author-email: software@relationrx.com
License: UNKNOWN
Platform: UNKNOWN
Requires-Python: >=3.8
Requires-Dist: openpyxl >=3.0.9
Requires-Dist: pandas <2.2.3,>=1.3.0
Requires-Dist: lightning <2.3.0,>=1.8.6
Requires-Dist: torch <2.3.0,>=1.9.0
Requires-Dist: torchvision <0.18.0,>=0.10.0
Requires-Dist: scikit-learn <1.4.3,>=1.0.2
Requires-Dist: tabulate <=0.9.0,>=0.7.0
Requires-Dist: xlrd >=2.0.1
